MultibodyPy/__init__.py
MultibodyPy/bodies.py
MultibodyPy/constraints.py
MultibodyPy/forces.py
MultibodyPy/group.py
MultibodyPy/multibody_system.py
MultibodyPy/solver.py
MultibodyPy/scipy_integrate_modified/__init__.py
MultibodyPy/scipy_integrate_modified/base.py
MultibodyPy/scipy_integrate_modified/bdf.py
MultibodyPy/scipy_integrate_modified/bdf_.py
MultibodyPy/scipy_integrate_modified/common.py
MultibodyPy/scipy_integrate_modified/radau.py
MultibodyPy-0.0.5.dist-info/LICENSE
MultibodyPy-0.0.5.dist-info/METADATA
MultibodyPy-0.0.5.dist-info/WHEEL
MultibodyPy-0.0.5.dist-info/top_level.txt
MultibodyPy-0.0.5.dist-info/RECORD
